vstutils/__init__.py
vstutils/__main__.py
vstutils/admin_urls.py
vstutils/asgi.py
vstutils/auth.py
vstutils/auth.pyi
vstutils/celery_beat_scheduler.py
vstutils/environment.py
vstutils/environment.pyi
vstutils/exceptions.py
vstutils/ldap_utils.py
vstutils/middleware.py
vstutils/middleware.pyi
vstutils/py.typed
vstutils/session.py
vstutils/settings.ini
vstutils/settings.py
vstutils/signals.py
vstutils/tasks.py
vstutils/tasks.pyi
vstutils/tests.py
vstutils/tools.py
vstutils/tools.pyi
vstutils/urls.py
vstutils/utils.py
vstutils/utils.pyi
vstutils/wsgi.py
vstutils/api/__init__.py
vstutils/api/actions.py
vstutils/api/actions.pyi
vstutils/api/admin.py
vstutils/api/apps.py
vstutils/api/auth.py
vstutils/api/base.py
vstutils/api/base.pyi
vstutils/api/decorators.py
vstutils/api/decorators.pyi
vstutils/api/endpoint.py
vstutils/api/fields.py
vstutils/api/filter_backends.py
vstutils/api/filters.py
vstutils/api/health.py
vstutils/api/meta.py
vstutils/api/metrics.py
vstutils/api/models.py
vstutils/api/pagination.py
vstutils/api/parsers.py
vstutils/api/password_reset.py
vstutils/api/permissions.py
vstutils/api/renderers.py
vstutils/api/responses.py
vstutils/api/responses.pyi
vstutils/api/routers.py
vstutils/api/routers.pyi
vstutils/api/serializers.py
vstutils/api/throttling.py
vstutils/api/validators.py
vstutils/api/views.py
vstutils/api/views.pyi
vstutils/api/migrations/0001_initial.py
vstutils/api/migrations/0002_two_factor.py
vstutils/api/migrations/0003_tfa_indexes.py
vstutils/api/migrations/0004_user_settings.py
vstutils/api/migrations/0005_db_translations.py
vstutils/api/migrations/0006_fix_user_settings.py
vstutils/api/migrations/0007_delete_customtranslations.py
vstutils/api/migrations/__init__.py
vstutils/api/registration/__init__.py
vstutils/api/registration/email_confirmation.py
vstutils/api/registration/serializers.py
vstutils/api/registration/utils.py
vstutils/api/registration/views.py
vstutils/api/schema/__init__.py
vstutils/api/schema/generators.py
vstutils-5.12.3.dist-info/LICENSE
vstutils-5.12.3.dist-info/METADATA
vstutils-5.12.3.dist-info/NOTICE
vstutils-5.12.3.dist-info/WHEEL
vstutils-5.12.3.dist-info/dependency_links.txt
vstutils-5.12.3.dist-info/entry_points.txt
vstutils-5.12.3.dist-info/top_level.txt
vstutils-5.12.3.dist-info/RECORD
