Metadata-Version: 2.1
Name: vstutils
Version: 5.12.3
Summary: VST Utils Framework for fast create web-application
Author-email: Sergei Kliuikov <sergey.k@vstconsulting.net>, Dmitriy Ovcharenko  <ovcharenkodd@gmail.com>
Maintainer-email: VST Consulting <sergey.k@vstconsulting.net>
License: Apache License 2.0
Project-URL: Issue Tracker, https://gitlab.com/vstconsulting/vstutils/issues
Project-URL: Source, https://gitlab.com/vstconsulting/vstutils
Project-URL: Releases, https://pypi.org/project/vstutils/#history
Project-URL: Documentation, https://vstutils.vstconsulting.net/
Keywords: spa,vue,pwa,framework,openapi,oauth2
Classifier: Development Status :: 5 - Production/Stable
Classifier: Environment :: Web Environment
Classifier: Framework :: Celery
Classifier: Framework :: Django
Classifier: Framework :: Django :: 5.1
Classifier: Framework :: Pydantic :: 2
Classifier: Operating System :: POSIX
Classifier: License :: OSI Approved :: Apache Software License
Classifier: Programming Language :: Python
Classifier: Programming Language :: Python :: 3
Classifier: Programming Language :: Python :: 3 :: Only
Classifier: Programming Language :: Python :: 3.10
Classifier: Programming Language :: Python :: 3.11
Classifier: Programming Language :: Python :: 3.12
Classifier: Programming Language :: Python :: 3.13
Classifier: Programming Language :: Python :: Implementation :: CPython
Classifier: Topic :: Software Development :: Libraries
Classifier: Topic :: Software Development :: User Interfaces
Classifier: Topic :: Internet :: WWW/HTTP
Classifier: Topic :: Internet :: WWW/HTTP :: Dynamic Content
Classifier: Topic :: Software Development :: Libraries :: Application Frameworks
Classifier: Topic :: Software Development :: Libraries :: Python Modules
Classifier: Topic :: Software Development :: User Interfaces
Classifier: Topic :: Utilities
Classifier: Intended Audience :: Developers
Classifier: Intended Audience :: Information Technology
Classifier: Typing :: Typed
Requires-Python: >=3.10
License-File: LICENSE
License-File: NOTICE
Requires-Dist: django ~=5.1.5
Requires-Dist: configparserc ~=3.0.2
Requires-Dist: Markdown ~=3.7
Requires-Dist: django-environ ~=0.12.0
Requires-Dist: djangorestframework ~=3.15.2
Requires-Dist: drf-yasg ==1.21.8
Requires-Dist: django-filter ==24.3
Requires-Dist: drf-orjson-renderer ==1.7.3
Requires-Dist: ormsgpack ~=1.7.0
Requires-Dist: pyyaml ~=6.0.2
Requires-Dist: uvicorn ~=0.34.0
Requires-Dist: fastapi-slim ~=0.115.6
Requires-Dist: aiofiles ~=24.1.0
Requires-Dist: cent ~=5.0.0
Requires-Dist: Authlib ~=1.4.0
Requires-Dist: django-htmlmin ~=0.11.0
Requires-Dist: pyotp ~=2.9.0
Requires-Dist: django-storages[libcloud] ==1.14.4
Provides-Extra: all
Requires-Dist: coverage ~=7.6.10 ; extra == 'all'
Requires-Dist: fakeldap ~=0.6.6 ; extra == 'all'
Requires-Dist: tblib ==3.0.0 ; extra == 'all'
Requires-Dist: beautifulsoup4 ~=4.12.3 ; extra == 'all'
Requires-Dist: httpx ~=0.27.2 ; extra == 'all'
Requires-Dist: celery[redis] ==5.5.0rc4 ; extra == 'all'
Requires-Dist: django-celery-beat ~=2.7.0 ; extra == 'all'
Requires-Dist: python-ldap ==3.4.4 ; extra == 'all'
Requires-Dist: sphinx ~=7.4.7 ; extra == 'all'
Requires-Dist: sphinx-autobuild ~=2024.4.16 ; extra == 'all'
Requires-Dist: sphinxcontrib-httpdomain ~=1.8.1 ; extra == 'all'
Requires-Dist: sphinxcontrib-websupport ~=2.0.0 ; extra == 'all'
Requires-Dist: sphinxcontrib-mermaid ~=0.9.2 ; extra == 'all'
Requires-Dist: sphinx-autodoc-typehints ~=2.2.3 ; extra == 'all'
Requires-Dist: sphinx-rtd-theme ~=2.0.0 ; extra == 'all'
Requires-Dist: redis[hiredis] ~=5.2.1 ; extra == 'all'
Requires-Dist: tarantool ~=1.2.0 ; extra == 'all'
Requires-Dist: pywebpush ==2.0.3 ; extra == 'all'
Requires-Dist: py-vapid <1.9.2 ; extra == 'all'
Requires-Dist: Pillow ~=11.1.0 ; extra == 'all'
Requires-Dist: django-storages[libcloud,s3] ==1.14.4 ; extra == 'all'
Provides-Extra: boto3
Requires-Dist: django-storages[libcloud,s3] ==1.14.4 ; extra == 'boto3'
Provides-Extra: doc
Requires-Dist: sphinx ~=7.4.7 ; extra == 'doc'
Requires-Dist: sphinx-autobuild ~=2024.4.16 ; extra == 'doc'
Requires-Dist: sphinxcontrib-httpdomain ~=1.8.1 ; extra == 'doc'
Requires-Dist: sphinxcontrib-websupport ~=2.0.0 ; extra == 'doc'
Requires-Dist: sphinxcontrib-mermaid ~=0.9.2 ; extra == 'doc'
Requires-Dist: sphinx-autodoc-typehints ~=2.2.3 ; extra == 'doc'
Requires-Dist: sphinx-rtd-theme ~=2.0.0 ; extra == 'doc'
Provides-Extra: ldap
Requires-Dist: python-ldap ==3.4.4 ; extra == 'ldap'
Provides-Extra: pil
Requires-Dist: Pillow ~=11.1.0 ; extra == 'pil'
Provides-Extra: prod
Requires-Dist: redis[hiredis] ~=5.2.1 ; extra == 'prod'
Requires-Dist: tarantool ~=1.2.0 ; extra == 'prod'
Requires-Dist: pywebpush ==2.0.3 ; extra == 'prod'
Requires-Dist: py-vapid <1.9.2 ; extra == 'prod'
Provides-Extra: rpc
Requires-Dist: celery[redis] ==5.5.0rc4 ; extra == 'rpc'
Requires-Dist: django-celery-beat ~=2.7.0 ; extra == 'rpc'
Provides-Extra: sqs
Requires-Dist: celery[redis] ==5.5.0rc4 ; extra == 'sqs'
Requires-Dist: django-celery-beat ~=2.7.0 ; extra == 'sqs'
Requires-Dist: pycurl ~=7.45.4 ; extra == 'sqs'
Provides-Extra: stubs
Requires-Dist: django-stubs[compatible-mypy] ==5.0.2 ; extra == 'stubs'
Requires-Dist: djangorestframework-stubs[compatible-mypy] ~=3.15.0 ; extra == 'stubs'
Requires-Dist: celery-stubs ~=0.1.3 ; extra == 'stubs'
Requires-Dist: drf-yasg-stubs ~=0.1.4 ; extra == 'stubs'
Requires-Dist: django-filter-stubs ~=0.1.3 ; extra == 'stubs'
Requires-Dist: types-PyMySQL ==1.1.0.1 ; extra == 'stubs'
Requires-Dist: types-Markdown ==3.5.0.3 ; extra == 'stubs'
Requires-Dist: types-docutils ==0.20.0.3 ; extra == 'stubs'
Requires-Dist: types-aiofiles ~=24.1.0.20240626 ; extra == 'stubs'
Requires-Dist: typing-extensions ~=4.12.2 ; extra == 'stubs'
Provides-Extra: test
Requires-Dist: coverage ~=7.6.10 ; extra == 'test'
Requires-Dist: fakeldap ~=0.6.6 ; extra == 'test'
Requires-Dist: tblib ==3.0.0 ; extra == 'test'
Requires-Dist: beautifulsoup4 ~=4.12.3 ; extra == 'test'
Requires-Dist: httpx ~=0.27.2 ; extra == 'test'
